.gitignore
MANIFEST.in
README.txt
setup.cfg
setup.py
docs/HISTORY.txt
docs/LICENSE.GPL
docs/LICENSE.txt
mfabrik/__init__.py
mfabrik.webandmobile.egg-info/PKG-INFO
mfabrik.webandmobile.egg-info/SOURCES.txt
mfabrik.webandmobile.egg-info/dependency_links.txt
mfabrik.webandmobile.egg-info/entry_points.txt
mfabrik.webandmobile.egg-info/namespace_packages.txt
mfabrik.webandmobile.egg-info/not-zip-safe
mfabrik.webandmobile.egg-info/paster_plugins.txt
mfabrik.webandmobile.egg-info/requires.txt
mfabrik.webandmobile.egg-info/top_level.txt
mfabrik/webandmobile/__init__.py
mfabrik/webandmobile/configure.zcml
mfabrik/webandmobile/tests.py