Metadata-Version: 1.1
Name: mfabrik.webandmobile
Version: 1.0.15
Summary: Mobile and multichannel content management for Plone
Home-page: http://webandmobile.mfabrik.com
Author: mFabrik Research Oy
Author-email: research@mfabrik.com
License: GPL
Keywords: plone cms multichannel mobile publishing app applications iphone android nokia blackberry
Platform: UNKNOWN
Classifier: Framework :: Plone
Classifier: Programming Language :: Python
